{"assets/images/anim/indian_flag.json":["assets/images/anim/indian_flag.json"],"assets/images/anim/online_shopping.json":["assets/images/anim/online_shopping.json"],"assets/images/anim/payment.json":["assets/images/anim/payment.json"],"assets/images/anim/qrcode.json":["assets/images/anim/qrcode.json"],"assets/images/anim/share.json":["assets/images/anim/share.json"],"assets/images/anim/success.json":["assets/images/anim/success.json"],"assets/images/anim/support.json":["assets/images/anim/support.json"],"assets/images/app_icon/app_icon_rounded.png":["assets/images/app_icon/app_icon_rounded.png"],"assets/images/png/charge.png":["assets/images/png/charge.png"],"assets/images/png/coupon.png":["assets/images/png/coupon.png"],"assets/images/png/customers.png":["assets/images/png/customers.png"],"assets/images/png/destination_map_marker.png":["assets/images/png/destination_map_marker.png"],"assets/images/png/order.png":["assets/images/png/order.png"],"assets/images/png/qr_code.png":["assets/images/png/qr_code.png"],"assets/images/png/rupee.png":["assets/images/png/rupee.png"],"assets/images/png/sell_guds_logo_with_title.png":["assets/images/png/sell_guds_logo_with_title.png"],"assets/images/svg/VIP.svg":["assets/images/svg/VIP.svg"],"assets/images/svg/add%20to%20collection.svg":["assets/images/svg/add%20to%20collection.svg"],"assets/images/svg/alarm.svg":["assets/images/svg/alarm.svg"],"assets/images/svg/application.svg":["assets/images/svg/application.svg"],"assets/images/svg/arrow2_down.svg":["assets/images/svg/arrow2_down.svg"],"assets/images/svg/arrow2_left.svg":["assets/images/svg/arrow2_left.svg"],"assets/images/svg/arrow2_right.svg":["assets/images/svg/arrow2_right.svg"],"assets/images/svg/arrow2_up.svg":["assets/images/svg/arrow2_up.svg"],"assets/images/svg/arrow_anti-clockwise.svg":["assets/images/svg/arrow_anti-clockwise.svg"],"assets/images/svg/arrow_down.svg":["assets/images/svg/arrow_down.svg"],"assets/images/svg/arrow_left.svg":["assets/images/svg/arrow_left.svg"],"assets/images/svg/arrow_lockwise.svg":["assets/images/svg/arrow_lockwise.svg"],"assets/images/svg/arrow_right.svg":["assets/images/svg/arrow_right.svg"],"assets/images/svg/arrow_up.svg":["assets/images/svg/arrow_up.svg"],"assets/images/svg/assisant.svg":["assets/images/svg/assisant.svg"],"assets/images/svg/bag.svg":["assets/images/svg/bag.svg"],"assets/images/svg/basket.svg":["assets/images/svg/basket.svg"],"assets/images/svg/basketball.svg":["assets/images/svg/basketball.svg"],"assets/images/svg/battery_empty.svg":["assets/images/svg/battery_empty.svg"],"assets/images/svg/battery_full.svg":["assets/images/svg/battery_full.svg"],"assets/images/svg/beer.svg":["assets/images/svg/beer.svg"],"assets/images/svg/bell.svg":["assets/images/svg/bell.svg"],"assets/images/svg/bookmark.svg":["assets/images/svg/bookmark.svg"],"assets/images/svg/briefcase.svg":["assets/images/svg/briefcase.svg"],"assets/images/svg/cake.svg":["assets/images/svg/cake.svg"],"assets/images/svg/calendar.svg":["assets/images/svg/calendar.svg"],"assets/images/svg/camera.svg":["assets/images/svg/camera.svg"],"assets/images/svg/candle.svg":["assets/images/svg/candle.svg"],"assets/images/svg/card.svg":["assets/images/svg/card.svg"],"assets/images/svg/cart.svg":["assets/images/svg/cart.svg"],"assets/images/svg/cash.svg":["assets/images/svg/cash.svg"],"assets/images/svg/caution.svg":["assets/images/svg/caution.svg"],"assets/images/svg/cd.svg":["assets/images/svg/cd.svg"],"assets/images/svg/chart.svg":["assets/images/svg/chart.svg"],"assets/images/svg/chat.svg":["assets/images/svg/chat.svg"],"assets/images/svg/choose.svg":["assets/images/svg/choose.svg"],"assets/images/svg/circle_arrow_down.svg":["assets/images/svg/circle_arrow_down.svg"],"assets/images/svg/circle_arrow_left.svg":["assets/images/svg/circle_arrow_left.svg"],"assets/images/svg/circle_arrow_right.svg":["assets/images/svg/circle_arrow_right.svg"],"assets/images/svg/circle_arrow_up.svg":["assets/images/svg/circle_arrow_up.svg"],"assets/images/svg/circle_choose.svg":["assets/images/svg/circle_choose.svg"],"assets/images/svg/circle_close.svg":["assets/images/svg/circle_close.svg"],"assets/images/svg/circle_minus.svg":["assets/images/svg/circle_minus.svg"],"assets/images/svg/circle_plus.svg":["assets/images/svg/circle_plus.svg"],"assets/images/svg/clip.svg":["assets/images/svg/clip.svg"],"assets/images/svg/clock.svg":["assets/images/svg/clock.svg"],"assets/images/svg/close.svg":["assets/images/svg/close.svg"],"assets/images/svg/clothes.svg":["assets/images/svg/clothes.svg"],"assets/images/svg/cloud1.svg":["assets/images/svg/cloud1.svg"],"assets/images/svg/cloud2.svg":["assets/images/svg/cloud2.svg"],"assets/images/svg/cloud_download.svg":["assets/images/svg/cloud_download.svg"],"assets/images/svg/cloud_upload.svg":["assets/images/svg/cloud_upload.svg"],"assets/images/svg/cocktail.svg":["assets/images/svg/cocktail.svg"],"assets/images/svg/coffe_tea.svg":["assets/images/svg/coffe_tea.svg"],"assets/images/svg/collection.svg":["assets/images/svg/collection.svg"],"assets/images/svg/compass.svg":["assets/images/svg/compass.svg"],"assets/images/svg/coordinates.svg":["assets/images/svg/coordinates.svg"],"assets/images/svg/coupon.svg":["assets/images/svg/coupon.svg"],"assets/images/svg/crown.svg":["assets/images/svg/crown.svg"],"assets/images/svg/cupcake.svg":["assets/images/svg/cupcake.svg"],"assets/images/svg/dashboard.svg":["assets/images/svg/dashboard.svg"],"assets/images/svg/desktop.svg":["assets/images/svg/desktop.svg"],"assets/images/svg/diamond.svg":["assets/images/svg/diamond.svg"],"assets/images/svg/dollar.svg":["assets/images/svg/dollar.svg"],"assets/images/svg/download.svg":["assets/images/svg/download.svg"],"assets/images/svg/earphone.svg":["assets/images/svg/earphone.svg"],"assets/images/svg/earth.svg":["assets/images/svg/earth.svg"],"assets/images/svg/empty.svg":["assets/images/svg/empty.svg"],"assets/images/svg/enter.svg":["assets/images/svg/enter.svg"],"assets/images/svg/euro.svg":["assets/images/svg/euro.svg"],"assets/images/svg/eye.svg":["assets/images/svg/eye.svg"],"assets/images/svg/fast%20forward.svg":["assets/images/svg/fast%20forward.svg"],"assets/images/svg/file.svg":["assets/images/svg/file.svg"],"assets/images/svg/file_choose.svg":["assets/images/svg/file_choose.svg"],"assets/images/svg/file_delete.svg":["assets/images/svg/file_delete.svg"],"assets/images/svg/file_empty.svg":["assets/images/svg/file_empty.svg"],"assets/images/svg/file_minus.svg":["assets/images/svg/file_minus.svg"],"assets/images/svg/file_plus.svg":["assets/images/svg/file_plus.svg"],"assets/images/svg/file_text.svg":["assets/images/svg/file_text.svg"],"assets/images/svg/filter.svg":["assets/images/svg/filter.svg"],"assets/images/svg/flag.svg":["assets/images/svg/flag.svg"],"assets/images/svg/flower.svg":["assets/images/svg/flower.svg"],"assets/images/svg/focus.svg":["assets/images/svg/focus.svg"],"assets/images/svg/gift.svg":["assets/images/svg/gift.svg"],"assets/images/svg/headphone%20.svg":["assets/images/svg/headphone%20.svg"],"assets/images/svg/heart.svg":["assets/images/svg/heart.svg"],"assets/images/svg/help.svg":["assets/images/svg/help.svg"],"assets/images/svg/hint.svg":["assets/images/svg/hint.svg"],"assets/images/svg/home.svg":["assets/images/svg/home.svg"],"assets/images/svg/hourglass.svg":["assets/images/svg/hourglass.svg"],"assets/images/svg/hyperlink.svg":["assets/images/svg/hyperlink.svg"],"assets/images/svg/hyperlink2.svg":["assets/images/svg/hyperlink2.svg"],"assets/images/svg/id%20card.svg":["assets/images/svg/id%20card.svg"],"assets/images/svg/juice.svg":["assets/images/svg/juice.svg"],"assets/images/svg/key.svg":["assets/images/svg/key.svg"],"assets/images/svg/lamp%20bulb.svg":["assets/images/svg/lamp%20bulb.svg"],"assets/images/svg/leaves.svg":["assets/images/svg/leaves.svg"],"assets/images/svg/life%20buoy.svg":["assets/images/svg/life%20buoy.svg"],"assets/images/svg/list.svg":["assets/images/svg/list.svg"],"assets/images/svg/list_choose.svg":["assets/images/svg/list_choose.svg"],"assets/images/svg/list_item.svg":["assets/images/svg/list_item.svg"],"assets/images/svg/locked.svg":["assets/images/svg/locked.svg"],"assets/images/svg/login.svg":["assets/images/svg/login.svg"],"assets/images/svg/logout.svg":["assets/images/svg/logout.svg"],"assets/images/svg/mail.svg":["assets/images/svg/mail.svg"],"assets/images/svg/medal.svg":["assets/images/svg/medal.svg"],"assets/images/svg/medal2.svg":["assets/images/svg/medal2.svg"],"assets/images/svg/megaphone.svg":["assets/images/svg/megaphone.svg"],"assets/images/svg/message.svg":["assets/images/svg/message.svg"],"assets/images/svg/microphone.svg":["assets/images/svg/microphone.svg"],"assets/images/svg/minus.svg":["assets/images/svg/minus.svg"],"assets/images/svg/moon.svg":["assets/images/svg/moon.svg"],"assets/images/svg/mouse.svg":["assets/images/svg/mouse.svg"],"assets/images/svg/music.svg":["assets/images/svg/music.svg"],"assets/images/svg/mute.svg":["assets/images/svg/mute.svg"],"assets/images/svg/navigation.svg":["assets/images/svg/navigation.svg"],"assets/images/svg/next.svg":["assets/images/svg/next.svg"],"assets/images/svg/no.svg":["assets/images/svg/no.svg"],"assets/images/svg/open%20file.svg":["assets/images/svg/open%20file.svg"],"assets/images/svg/order%20form.svg":["assets/images/svg/order%20form.svg"],"assets/images/svg/pad.svg":["assets/images/svg/pad.svg"],"assets/images/svg/pause.svg":["assets/images/svg/pause.svg"],"assets/images/svg/phone.svg":["assets/images/svg/phone.svg"],"assets/images/svg/picture.svg":["assets/images/svg/picture.svg"],"assets/images/svg/pie%20chart.svg":["assets/images/svg/pie%20chart.svg"],"assets/images/svg/pin.svg":["assets/images/svg/pin.svg"],"assets/images/svg/plane.svg":["assets/images/svg/plane.svg"],"assets/images/svg/planet.svg":["assets/images/svg/planet.svg"],"assets/images/svg/play.svg":["assets/images/svg/play.svg"],"assets/images/svg/plus.svg":["assets/images/svg/plus.svg"],"assets/images/svg/pound.svg":["assets/images/svg/pound.svg"],"assets/images/svg/power.svg":["assets/images/svg/power.svg"],"assets/images/svg/previous.svg":["assets/images/svg/previous.svg"],"assets/images/svg/rain.svg":["assets/images/svg/rain.svg"],"assets/images/svg/refresh.svg":["assets/images/svg/refresh.svg"],"assets/images/svg/rewind.svg":["assets/images/svg/rewind.svg"],"assets/images/svg/rocket.svg":["assets/images/svg/rocket.svg"],"assets/images/svg/ruler.svg":["assets/images/svg/ruler.svg"],"assets/images/svg/scissors.svg":["assets/images/svg/scissors.svg"],"assets/images/svg/search.svg":["assets/images/svg/search.svg"],"assets/images/svg/setting_cog.svg":["assets/images/svg/setting_cog.svg"],"assets/images/svg/setting_edit.svg":["assets/images/svg/setting_edit.svg"],"assets/images/svg/setting_wrench.svg":["assets/images/svg/setting_wrench.svg"],"assets/images/svg/signal.svg":["assets/images/svg/signal.svg"],"assets/images/svg/snow%20and%20rain.svg":["assets/images/svg/snow%20and%20rain.svg"],"assets/images/svg/snow.svg":["assets/images/svg/snow.svg"],"assets/images/svg/splash_image.svg":["assets/images/svg/splash_image.svg"],"assets/images/svg/star.svg":["assets/images/svg/star.svg"],"assets/images/svg/steering%20wheel.svg":["assets/images/svg/steering%20wheel.svg"],"assets/images/svg/stop.svg":["assets/images/svg/stop.svg"],"assets/images/svg/sun.svg":["assets/images/svg/sun.svg"],"assets/images/svg/tag.svg":["assets/images/svg/tag.svg"],"assets/images/svg/team.svg":["assets/images/svg/team.svg"],"assets/images/svg/telephone%20directory.svg":["assets/images/svg/telephone%20directory.svg"],"assets/images/svg/telephone.svg":["assets/images/svg/telephone.svg"],"assets/images/svg/text.svg":["assets/images/svg/text.svg"],"assets/images/svg/thunder.svg":["assets/images/svg/thunder.svg"],"assets/images/svg/tie.svg":["assets/images/svg/tie.svg"],"assets/images/svg/umbrella.svg":["assets/images/svg/umbrella.svg"],"assets/images/svg/unlocked.svg":["assets/images/svg/unlocked.svg"],"assets/images/svg/upload.svg":["assets/images/svg/upload.svg"],"assets/images/svg/user.svg":["assets/images/svg/user.svg"],"assets/images/svg/van.svg":["assets/images/svg/van.svg"],"assets/images/svg/volume.svg":["assets/images/svg/volume.svg"],"assets/images/svg/wallet.svg":["assets/images/svg/wallet.svg"],"assets/images/svg/warehouse.svg":["assets/images/svg/warehouse.svg"],"assets/images/svg/wifi.svg":["assets/images/svg/wifi.svg"],"assets/images/svg/wine.svg":["assets/images/svg/wine.svg"],"assets/images/svg/yuan.svg":["assets/images/svg/yuan.svg"],"assets/images/svg/zoom%20in.svg":["assets/images/svg/zoom%20in.svg"],"assets/images/svg/zoom%20out.svg":["assets/images/svg/zoom%20out.svg"]}